pythematics/__init__.py
pythematics/basic.py
pythematics/constants.py
pythematics/functions.py
pythematics/linear.py
pythematics/num_theory.py
pythematics/polynomials.py
pythematics/powers.py
pythematics/random.py
pythematics/setup.py
pythematics/trigonometric.py
pythematics-4.0.0.dist-info/METADATA
pythematics-4.0.0.dist-info/WHEEL
pythematics-4.0.0.dist-info/top_level.txt
pythematics-4.0.0.dist-info/RECORD
