Metadata-Version: 2.1
Name: pythematics
Version: 4.0.0
Summary: Python Math library for Matrix and Polynomial manipulation extending to the complex plane
Home-page: https://github.com/Greece4ever/pythematics
Author: Leonidios
Author-email: programertv633@gmail.com
License: UNKNOWN
Platform: UNKNOWN
Classifier: Programming Language :: Python :: 3
Classifier: License :: OSI Approved :: MIT License
Classifier: Operating System :: OS Independent
Requires-Python: >=3.3
